my_first_projecr_demo_1/__init__.py
my_first_projecr_demo_1/create_ds_records.py
my_first_projecr_demo_1/create_records_in_datastore.py
my_first_projecr_demo_1/gcp_auth.py
my_first_projecr_demo_1-0.3.0.dist-info/WHEEL
my_first_projecr_demo_1-0.3.0.dist-info/METADATA
my_first_projecr_demo_1-0.3.0.dist-info/RECORD
