Metadata-Version: 2.1
Name: my-first-projecr-demo-1
Version: 0.3.0
Summary: 
Author: Your Name
Author-email: you@example.com
Requires-Python: >=3.10,<4.0
Classifier: Programming Language :: Python :: 3
Classifier: Programming Language :: Python :: 3.10
Requires-Dist: apache-airflow (>=2.5.0,<3.0.0)
Requires-Dist: appengine-python-standard (>=1.0.0,<2.0.0)
Requires-Dist: google-cloud-datastore (>=2.11.0,<3.0.0)
Requires-Dist: google-cloud-storage (>=2.7.0,<3.0.0)
Requires-Dist: pytest (>=7.2.0,<8.0.0)
Requires-Dist: requests (>=2.28.1,<3.0.0)
